pyord-0.3.0.dist-info/METADATA
pyord-0.3.0.dist-info/WHEEL
pyord/__init__.py
pyord/__init__.pyi
pyord/py.typed
pyord/pyord.abi3.so
pyord-0.3.0.dist-info/RECORD
